{
    "busType": "大学行", 
    "tableName": "講義期間中大学行平日", 
    "北坂戸駅発": [
        "8:32", 
        "8:47", 
        "8:55", 
        "9:38", 
        "10:21", 
        "10:48", 
        "11:16", 
        "11:47", 
        "12:47", 
        "13:16", 
        "13:47", 
        "14:16", 
        "14:47", 
        "15:30", 
        "16:00", 
        "16:48"
    ], 
    "熊谷駅発": [
        "8:20", 
        "8:35", 
        "10:00", 
        "10:15", 
        "12:30", 
        "12:45", 
        "14:10", 
        "15:55"
    ], 
    "高坂駅発": [
        "8:34", 
        "8:42", 
        "8:50", 
        "8:55", 
        "9:00", 
        "9:05", 
        "9:10", 
        "9:15", 
        "9:20", 
        "9:25", 
        "9:30", 
        "9:35", 
        "9:50", 
        "9:55", 
        "10:05", 
        "10:10", 
        "10:16", 
        "10:24", 
        "10:29", 
        "10:40", 
        "10:45", 
        "10:50", 
        "10:53", 
        "10:57", 
        "11:04", 
        "11:11", 
        "11:19", 
        "11:34", 
        "11:49", 
        "12:04", 
        "12:19", 
        "12:34", 
        "12:49", 
        "13:04", 
        "13:09", 
        "13:19", 
        "13:34", 
        "13:49", 
        "14:04", 
        "14:19", 
        "14:34", 
        "14:49", 
        "14:53", 
        "15:04", 
        "15:19", 
        "15:34", 
        "15:49", 
        "16:04", 
        "16:21", 
        "16:35", 
        "16:49", 
        "17:16", 
        "17:35", 
        "17:52", 
        "18:15"
    ], 
    "高崎駅発": [
        "7:45"
    ], 
    "鴻巣駅発": [
        "8:30"
    ]
}